<annotation>
  <filename>13656.png</filename>
  <size>
    <width>102</width>
    <height>41</height>
    <depth>3</depth>
  </size>
  <object>
    <name>1</name>
    <bndbox>
      <xmin>34</xmin>
      <ymin>9</ymin>
      <xmax>44</xmax>
      <ymax>30</ymax>
    </bndbox>
  </object>
  <object>
    <name>2</name>
    <bndbox>
      <xmin>43</xmin>
      <ymin>10</ymin>
      <xmax>55</xmax>
      <ymax>31</ymax>
    </bndbox>
  </object>
  <object>
    <name>9</name>
    <bndbox>
      <xmin>54</xmin>
      <ymin>9</ymin>
      <xmax>67</xmax>
      <ymax>30</ymax>
    </bndbox>
  </object>
</annotation>
