<annotation>
  <filename>14318.png</filename>
  <size>
    <width>201</width>
    <height>78</height>
    <depth>3</depth>
  </size>
  <object>
    <name>2</name>
    <bndbox>
      <xmin>74</xmin>
      <ymin>19</ymin>
      <xmax>95</xmax>
      <ymax>53</ymax>
    </bndbox>
  </object>
  <object>
    <name>6</name>
    <bndbox>
      <xmin>93</xmin>
      <ymin>20</ymin>
      <xmax>112</xmax>
      <ymax>54</ymax>
    </bndbox>
  </object>
  <object>
    <name>5</name>
    <bndbox>
      <xmin>111</xmin>
      <ymin>21</ymin>
      <xmax>128</xmax>
      <ymax>55</ymax>
    </bndbox>
  </object>
</annotation>
