<annotation>
  <filename>22670.png</filename>
  <size>
    <width>263</width>
    <height>99</height>
    <depth>3</depth>
  </size>
  <object>
    <name>2</name>
    <bndbox>
      <xmin>73</xmin>
      <ymin>28</ymin>
      <xmax>104</xmax>
      <ymax>94</ymax>
    </bndbox>
  </object>
  <object>
    <name>7</name>
    <bndbox>
      <xmin>114</xmin>
      <ymin>25</ymin>
      <xmax>141</xmax>
      <ymax>91</ymax>
    </bndbox>
  </object>
  <object>
    <name>7</name>
    <bndbox>
      <xmin>153</xmin>
      <ymin>15</ymin>
      <xmax>201</xmax>
      <ymax>81</ymax>
    </bndbox>
  </object>
</annotation>
