<annotation>
  <filename>29185.png</filename>
  <size>
    <width>172</width>
    <height>68</height>
    <depth>3</depth>
  </size>
  <object>
    <name>8</name>
    <bndbox>
      <xmin>66</xmin>
      <ymin>21</ymin>
      <xmax>82</xmax>
      <ymax>44</ymax>
    </bndbox>
  </object>
  <object>
    <name>10</name>
    <bndbox>
      <xmin>82</xmin>
      <ymin>24</ymin>
      <xmax>96</xmax>
      <ymax>47</ymax>
    </bndbox>
  </object>
  <object>
    <name>1</name>
    <bndbox>
      <xmin>95</xmin>
      <ymin>21</ymin>
      <xmax>103</xmax>
      <ymax>44</ymax>
    </bndbox>
  </object>
</annotation>
