<annotation>
  <filename>6487.png</filename>
  <size>
    <width>62</width>
    <height>21</height>
    <depth>3</depth>
  </size>
  <object>
    <name>2</name>
    <bndbox>
      <xmin>18</xmin>
      <ymin>3</ymin>
      <xmax>25</xmax>
      <ymax>14</ymax>
    </bndbox>
  </object>
  <object>
    <name>4</name>
    <bndbox>
      <xmin>25</xmin>
      <ymin>5</ymin>
      <xmax>33</xmax>
      <ymax>16</ymax>
    </bndbox>
  </object>
  <object>
    <name>2</name>
    <bndbox>
      <xmin>34</xmin>
      <ymin>5</ymin>
      <xmax>40</xmax>
      <ymax>16</ymax>
    </bndbox>
  </object>
  <object>
    <name>3</name>
    <bndbox>
      <xmin>40</xmin>
      <ymin>4</ymin>
      <xmax>48</xmax>
      <ymax>15</ymax>
    </bndbox>
  </object>
</annotation>
