<annotation>
  <filename>6524.png</filename>
  <size>
    <width>127</width>
    <height>50</height>
    <depth>3</depth>
  </size>
  <object>
    <name>2</name>
    <bndbox>
      <xmin>47</xmin>
      <ymin>16</ymin>
      <xmax>61</xmax>
      <ymax>36</ymax>
    </bndbox>
  </object>
  <object>
    <name>2</name>
    <bndbox>
      <xmin>59</xmin>
      <ymin>16</ymin>
      <xmax>70</xmax>
      <ymax>36</ymax>
    </bndbox>
  </object>
  <object>
    <name>5</name>
    <bndbox>
      <xmin>69</xmin>
      <ymin>15</ymin>
      <xmax>84</xmax>
      <ymax>35</ymax>
    </bndbox>
  </object>
</annotation>
