<annotation>
  <filename>10502.png</filename>
  <size>
    <width>276</width>
    <height>131</height>
    <depth>3</depth>
  </size>
  <object>
    <name>1</name>
    <bndbox>
      <xmin>61</xmin>
      <ymin>37</ymin>
      <xmax>80</xmax>
      <ymax>75</ymax>
    </bndbox>
  </object>
  <object>
    <name>10</name>
    <bndbox>
      <xmin>75</xmin>
      <ymin>28</ymin>
      <xmax>93</xmax>
      <ymax>66</ymax>
    </bndbox>
  </object>
  <object>
    <name>2</name>
    <bndbox>
      <xmin>93</xmin>
      <ymin>22</ymin>
      <xmax>106</xmax>
      <ymax>60</ymax>
    </bndbox>
  </object>
  <object>
    <name>2</name>
    <bndbox>
      <xmin>106</xmin>
      <ymin>10</ymin>
      <xmax>124</xmax>
      <ymax>48</ymax>
    </bndbox>
  </object>
</annotation>
