<annotation>
  <filename>13740.png</filename>
  <size>
    <width>178</width>
    <height>83</height>
    <depth>3</depth>
  </size>
  <object>
    <name>1</name>
    <bndbox>
      <xmin>27</xmin>
      <ymin>23</ymin>
      <xmax>41</xmax>
      <ymax>59</ymax>
    </bndbox>
  </object>
  <object>
    <name>3</name>
    <bndbox>
      <xmin>39</xmin>
      <ymin>22</ymin>
      <xmax>62</xmax>
      <ymax>58</ymax>
    </bndbox>
  </object>
  <object>
    <name>1</name>
    <bndbox>
      <xmin>61</xmin>
      <ymin>23</ymin>
      <xmax>76</xmax>
      <ymax>59</ymax>
    </bndbox>
  </object>
  <object>
    <name>6</name>
    <bndbox>
      <xmin>74</xmin>
      <ymin>22</ymin>
      <xmax>100</xmax>
      <ymax>58</ymax>
    </bndbox>
  </object>
</annotation>
