<annotation>
  <filename>1551.png</filename>
  <size>
    <width>51</width>
    <height>24</height>
    <depth>3</depth>
  </size>
  <object>
    <name>3</name>
    <bndbox>
      <xmin>18</xmin>
      <ymin>4</ymin>
      <xmax>25</xmax>
      <ymax>20</ymax>
    </bndbox>
  </object>
  <object>
    <name>3</name>
    <bndbox>
      <xmin>23</xmin>
      <ymin>4</ymin>
      <xmax>28</xmax>
      <ymax>20</ymax>
    </bndbox>
  </object>
  <object>
    <name>7</name>
    <bndbox>
      <xmin>28</xmin>
      <ymin>3</ymin>
      <xmax>33</xmax>
      <ymax>19</ymax>
    </bndbox>
  </object>
</annotation>
