<annotation>
  <filename>22752.png</filename>
  <size>
    <width>146</width>
    <height>61</height>
    <depth>3</depth>
  </size>
  <object>
    <name>3</name>
    <bndbox>
      <xmin>39</xmin>
      <ymin>3</ymin>
      <xmax>61</xmax>
      <ymax>57</ymax>
    </bndbox>
  </object>
  <object>
    <name>1</name>
    <bndbox>
      <xmin>61</xmin>
      <ymin>2</ymin>
      <xmax>77</xmax>
      <ymax>56</ymax>
    </bndbox>
  </object>
  <object>
    <name>7</name>
    <bndbox>
      <xmin>78</xmin>
      <ymin>3</ymin>
      <xmax>103</xmax>
      <ymax>57</ymax>
    </bndbox>
  </object>
</annotation>
