<annotation>
  <filename>29193.png</filename>
  <size>
    <width>222</width>
    <height>83</height>
    <depth>3</depth>
  </size>
  <object>
    <name>2</name>
    <bndbox>
      <xmin>65</xmin>
      <ymin>6</ymin>
      <xmax>97</xmax>
      <ymax>71</ymax>
    </bndbox>
  </object>
  <object>
    <name>6</name>
    <bndbox>
      <xmin>96</xmin>
      <ymin>6</ymin>
      <xmax>135</xmax>
      <ymax>71</ymax>
    </bndbox>
  </object>
  <object>
    <name>3</name>
    <bndbox>
      <xmin>134</xmin>
      <ymin>6</ymin>
      <xmax>164</xmax>
      <ymax>71</ymax>
    </bndbox>
  </object>
</annotation>
