<annotation>
  <filename>29250.png</filename>
  <size>
    <width>114</width>
    <height>39</height>
    <depth>3</depth>
  </size>
  <object>
    <name>2</name>
    <bndbox>
      <xmin>30</xmin>
      <ymin>1</ymin>
      <xmax>46</xmax>
      <ymax>31</ymax>
    </bndbox>
  </object>
  <object>
    <name>5</name>
    <bndbox>
      <xmin>44</xmin>
      <ymin>3</ymin>
      <xmax>61</xmax>
      <ymax>33</ymax>
    </bndbox>
  </object>
  <object>
    <name>1</name>
    <bndbox>
      <xmin>59</xmin>
      <ymin>3</ymin>
      <xmax>73</xmax>
      <ymax>33</ymax>
    </bndbox>
  </object>
  <object>
    <name>1</name>
    <bndbox>
      <xmin>72</xmin>
      <ymin>3</ymin>
      <xmax>88</xmax>
      <ymax>33</ymax>
    </bndbox>
  </object>
</annotation>
