<annotation>
  <filename>29941.png</filename>
  <size>
    <width>237</width>
    <height>96</height>
    <depth>3</depth>
  </size>
  <object>
    <name>1</name>
    <bndbox>
      <xmin>120</xmin>
      <ymin>38</ymin>
      <xmax>139</xmax>
      <ymax>79</ymax>
    </bndbox>
  </object>
  <object>
    <name>8</name>
    <bndbox>
      <xmin>129</xmin>
      <ymin>31</ymin>
      <xmax>153</xmax>
      <ymax>72</ymax>
    </bndbox>
  </object>
  <object>
    <name>10</name>
    <bndbox>
      <xmin>143</xmin>
      <ymin>17</ymin>
      <xmax>168</xmax>
      <ymax>58</ymax>
    </bndbox>
  </object>
</annotation>
