<annotation>
  <filename>382.png</filename>
  <size>
    <width>84</width>
    <height>35</height>
    <depth>3</depth>
  </size>
  <object>
    <name>6</name>
    <bndbox>
      <xmin>29</xmin>
      <ymin>7</ymin>
      <xmax>36</xmax>
      <ymax>26</ymax>
    </bndbox>
  </object>
  <object>
    <name>5</name>
    <bndbox>
      <xmin>35</xmin>
      <ymin>6</ymin>
      <xmax>42</xmax>
      <ymax>25</ymax>
    </bndbox>
  </object>
  <object>
    <name>8</name>
    <bndbox>
      <xmin>42</xmin>
      <ymin>7</ymin>
      <xmax>50</xmax>
      <ymax>26</ymax>
    </bndbox>
  </object>
</annotation>
