<annotation>
  <filename>6230.png</filename>
  <size>
    <width>96</width>
    <height>41</height>
    <depth>3</depth>
  </size>
  <object>
    <name>1</name>
    <bndbox>
      <xmin>34</xmin>
      <ymin>3</ymin>
      <xmax>44</xmax>
      <ymax>33</ymax>
    </bndbox>
  </object>
  <object>
    <name>1</name>
    <bndbox>
      <xmin>40</xmin>
      <ymin>8</ymin>
      <xmax>53</xmax>
      <ymax>38</ymax>
    </bndbox>
  </object>
  <object>
    <name>6</name>
    <bndbox>
      <xmin>52</xmin>
      <ymin>5</ymin>
      <xmax>63</xmax>
      <ymax>35</ymax>
    </bndbox>
  </object>
</annotation>
