<annotation>
  <filename>6267.png</filename>
  <size>
    <width>187</width>
    <height>83</height>
    <depth>3</depth>
  </size>
  <object>
    <name>2</name>
    <bndbox>
      <xmin>52</xmin>
      <ymin>12</ymin>
      <xmax>84</xmax>
      <ymax>74</ymax>
    </bndbox>
  </object>
  <object>
    <name>7</name>
    <bndbox>
      <xmin>72</xmin>
      <ymin>10</ymin>
      <xmax>107</xmax>
      <ymax>72</ymax>
    </bndbox>
  </object>
  <object>
    <name>8</name>
    <bndbox>
      <xmin>98</xmin>
      <ymin>9</ymin>
      <xmax>130</xmax>
      <ymax>71</ymax>
    </bndbox>
  </object>
</annotation>
