<annotation>
  <filename>9040.png</filename>
  <size>
    <width>181</width>
    <height>76</height>
    <depth>3</depth>
  </size>
  <object>
    <name>2</name>
    <bndbox>
      <xmin>41</xmin>
      <ymin>13</ymin>
      <xmax>72</xmax>
      <ymax>59</ymax>
    </bndbox>
  </object>
  <object>
    <name>3</name>
    <bndbox>
      <xmin>71</xmin>
      <ymin>3</ymin>
      <xmax>93</xmax>
      <ymax>49</ymax>
    </bndbox>
  </object>
  <object>
    <name>7</name>
    <bndbox>
      <xmin>100</xmin>
      <ymin>2</ymin>
      <xmax>129</xmax>
      <ymax>48</ymax>
    </bndbox>
  </object>
</annotation>
